sysctl
sysctl/_sysctl
sysctl/tests
