Metadata-Version: 1.1
Name: sysctl
Version: 0.3.3
Summary: Wrapper for the sysctl* system functions
Home-page: https://github.com/williambr/py-sysctl
Author: William Grzybowski
Author-email: wg@FreeBSD.org
License: BSD
Keywords: sysctl
Platform: any
Classifier: Development Status :: 4 - Beta
Classifier: Intended Audience :: Developers
Classifier: License :: OSI Approved :: BSD License
Classifier: Operating System :: POSIX :: BSD :: FreeBSD
Classifier: Programming Language :: Python
Classifier: Programming Language :: Python :: 2.7
Classifier: Programming Language :: Python :: 3.2
Classifier: Programming Language :: Python :: 3.3
Classifier: Programming Language :: Python :: Implementation :: CPython
